scripts/GAM_fastq_accession2filename.txt.gz
scripts/__init__.py
scripts/_version.py
scripts/cp_files2diffbucket.py
scripts/delete_item_or_fields.py
scripts/empty_patch_items.py
scripts/generate_wfr_from_pf.py
scripts/geo2fdn.py
scripts/get_item_ids_from_search.py
scripts/get_linked_item_ids.py
scripts/item_fetcher.py
scripts/item_loader.py
scripts/load_items_json.py
scripts/ontology_term_loader.py
scripts/parse_damid_pf.py
scripts/patch_field_for_many_items.py
scripts/pfs2opfs.py
scripts/quick_patcher.py
scripts/rxiv2ja.py
scripts/tag_release_freeze.py
scripts/tagger.py
dcicwrangling-3.2.0.dist-info/METADATA
dcicwrangling-3.2.0.dist-info/WHEEL
dcicwrangling-3.2.0.dist-info/entry_points.txt
dcicwrangling-3.2.0.dist-info/RECORD
