Metadata-Version: 2.1
Name: dcicwrangling
Version: 3.2.0
Summary: Scripts and Jupyter notebooks for 4DN wrangling
Home-page: https://github.com/4dn-dcic/dcicwrangling
License: MIT
Author: 4DN-DCIC Team
Author-email: support@4dnucleome.org
Requires-Python: >=3.8.0,<3.12
Classifier: License :: OSI Approved :: MIT License
Classifier: Programming Language :: Python :: 3
Classifier: Programming Language :: Python :: 3.8
Classifier: Programming Language :: Python :: 3.9
Classifier: Programming Language :: Python :: 3.10
Classifier: Programming Language :: Python :: 3.11
Requires-Dist: Biopython (>=1.80,<2.0)
Requires-Dist: GEOparse (>=2.0.1,<3.0.0)
Requires-Dist: dcicutils (>=8.0.0,<9.0.0)
Requires-Dist: jupyterlab (==3.2.8)
Requires-Dist: openpyxl (>=3.0.9,<4.0.0)
Project-URL: Repository, https://github.com/4dn-dcic/dcicwrangling
